file/__init__.py
easy_file_process-0.1.2.dist-info/LICENSE
easy_file_process-0.1.2.dist-info/METADATA
easy_file_process-0.1.2.dist-info/WHEEL
easy_file_process-0.1.2.dist-info/top_level.txt
easy_file_process-0.1.2.dist-info/RECORD
